sioscgi/__init__.py
sioscgi/py.typed
sioscgi/request.py
sioscgi/response.py
sioscgi-5.0.0.dist-info/LICENSE
sioscgi-5.0.0.dist-info/METADATA
sioscgi-5.0.0.dist-info/WHEEL
sioscgi-5.0.0.dist-info/top_level.txt
sioscgi-5.0.0.dist-info/zip-safe
sioscgi-5.0.0.dist-info/RECORD
