Metadata-Version: 2.1
Name: sioscgi
Version: 5.0.0
Summary: A sans-I/O implementation of the SCGI specification.
Home-page: https://gitlab.com/Hawk777/sioscgi
Author: Christopher Head
Classifier: Development Status :: 5 - Production/Stable
Classifier: Intended Audience :: Developers
Classifier: License :: OSI Approved :: GNU General Public License v3 (GPLv3)
Classifier: Operating System :: OS Independent
Classifier: Programming Language :: Python :: 3
Classifier: Topic :: Internet :: WWW/HTTP :: Dynamic Content :: CGI Tools/Libraries
Classifier: Topic :: Software Development :: Libraries :: Python Modules
Requires-Python: >=3.10
License-File: LICENSE
